rdmysql3/__init__.py
rdmysql3/archive.py
rdmysql3/daily.py
rdmysql3/database.py
rdmysql3/expr.py
rdmysql3/row.py
rdmysql3/table.py
rdmysql3/utils.py
rdmysql3-0.3.8.dist-info/LICENSE
rdmysql3-0.3.8.dist-info/METADATA
rdmysql3-0.3.8.dist-info/WHEEL
rdmysql3-0.3.8.dist-info/RECORD
